radardef/__init__.py
radardef/py.typed
radardef/radar_def.py
radardef/version.py
radardef/cli/__init__.py
radardef/cli/commands_cli.py
radardef/cli/convert_cli.py
radardef/cli/download_cli.py
radardef/cli/format_cli.py
radardef/collections/__init__.py
radardef/collections/converter_collection.py
radardef/collections/data_loader_collection.py
radardef/collections/format_collection.py
radardef/components/__init__.py
radardef/components/converter_template.py
radardef/components/data_loader_template.py
radardef/components/radar_station_template.py
radardef/components/validator_template.py
radardef/download/__init__.py
radardef/download/eiscat/__init__.py
radardef/download/eiscat/download.py
radardef/radar_stations/__init__.py
radardef/radar_stations/eiscat/__init__.py
radardef/radar_stations/eiscat/eiscat_3d.py
radardef/radar_stations/eiscat/eiscat_uhf.py
radardef/radar_stations/eiscat/eiscat_vhf.py
radardef/radar_stations/eiscat/esr.py
radardef/radar_stations/eiscat/tsdr.py
radardef/radar_stations/eiscat/beams/__init__.py
radardef/radar_stations/eiscat/beams/e3d/__init__.py
radardef/radar_stations/eiscat/beams/e3d/eiscat_3d_beam.py
radardef/radar_stations/eiscat/beams/e3d/data/__init__.py
radardef/radar_stations/eiscat/beams/e3d/data/e3d_subgroup_positions.txt
radardef/radar_stations/eiscat/beams/esr/__init__.py
radardef/radar_stations/eiscat/beams/esr/esr_beam.py
radardef/radar_stations/eiscat/beams/tsdr/__init__.py
radardef/radar_stations/eiscat/beams/tsdr/tsdr_beam.py
radardef/radar_stations/eiscat/beams/uhf/__init__.py
radardef/radar_stations/eiscat/beams/uhf/eiscat_uhf_beam.py
radardef/radar_stations/eiscat/beams/uhf/data/__init__.py
radardef/radar_stations/eiscat/beams/uhf/data/eiscat_uhf_bp.txt
radardef/radar_stations/eiscat/beams/vhf/__init__.py
radardef/radar_stations/eiscat/beams/vhf/eiscat_vhf_beam.py
radardef/radar_stations/eiscat/converters/__init__.py
radardef/radar_stations/eiscat/converters/eiscat_matbz_to_drf.py
radardef-0.2.0.dist-info/licenses/LICENSE
radardef-0.2.0.dist-info/METADATA
radardef-0.2.0.dist-info/WHEEL
radardef-0.2.0.dist-info/entry_points.txt
radardef-0.2.0.dist-info/top_level.txt
radardef-0.2.0.dist-info/RECORD
