Metadata-Version: 2.4
Name: radardef
Version: 0.2.0
Summary: Radar station specifications and data utilities
Author-email: Daniel Kastinen <daniel.kastinen@irf.se>, Hampus Andersson <hampus.andersson@irf.se>
Maintainer-email: Daniel Kastinen <daniel.kastinen@irf.se>, Hampus Andersson <hampus.andersson@irf.se>
License: MIT License
Project-URL: Documentation, https://danielk.developer.irf.se/radardef/
Project-URL: Repository, https://github.com/danielk333/radardef
Classifier: Intended Audience :: Science/Research
Classifier: Programming Language :: Python :: 3
Classifier: Topic :: Scientific/Engineering :: Physics
Classifier: Operating System :: OS Independent
Classifier: License :: OSI Approved :: MIT License
Requires-Python: >=3.11
License-File: LICENSE
Requires-Dist: pyant>=1.1.0
Requires-Dist: spacecoords>=0.1.2
Requires-Dist: numpy>=1.19.5
Requires-Dist: scipy>=1.4.1
Requires-Dist: h5py>=3.4.0
Requires-Dist: digital_rf>=2.6.6
Requires-Dist: tqdm>=4.66.1
Requires-Dist: requests>=2.28.2
Requires-Dist: lxml
Provides-Extra: develop
Requires-Dist: pytest; extra == "develop"
Requires-Dist: flake8; extra == "develop"
Requires-Dist: wheel; extra == "develop"
Requires-Dist: build; extra == "develop"
Requires-Dist: twine; extra == "develop"
Requires-Dist: auditwheel; extra == "develop"
Requires-Dist: pytest-cov; extra == "develop"
Requires-Dist: black; extra == "develop"
Requires-Dist: isort; extra == "develop"
Provides-Extra: type-checker
Requires-Dist: mypy>=1.18.2; extra == "type-checker"
Requires-Dist: xenon; extra == "type-checker"
Provides-Extra: profiling
Requires-Dist: yappi>=1.4.0; extra == "profiling"
Provides-Extra: tests
Requires-Dist: pytest; extra == "tests"
Requires-Dist: pytest-cov; extra == "tests"
Provides-Extra: documentation
Requires-Dist: docstr-coverage; extra == "documentation"
Requires-Dist: mkdocs-material; extra == "documentation"
Requires-Dist: mkdocstrings[python]; extra == "documentation"
Requires-Dist: mkdocs-jupyter; extra == "documentation"
Requires-Dist: mkdocs-gen-files; extra == "documentation"
Requires-Dist: mkdocs-literate-nav; extra == "documentation"
Requires-Dist: mkdocs-section-index; extra == "documentation"
Requires-Dist: matplotlib; extra == "documentation"
Provides-Extra: mpi
Requires-Dist: mpi4py; extra == "mpi"
Provides-Extra: skymaps
Requires-Dist: pygdsm; extra == "skymaps"
Requires-Dist: astropy-healpix; extra == "skymaps"
Dynamic: license-file
